chunker/__init__.py
chunker/_version.py
chunker/auto.py
chunker/chunker.py
chunker/chunker_config.py
chunker/core.py
chunker/exceptions.py
chunker/grammar_manager.py
chunker/incremental.py
chunker/multi_language.py
chunker/optimization.py
chunker/packing.py
chunker/parallel.py
chunker/parser.py
chunker/plugin_manager.py
chunker/py.typed
chunker/query_advanced.py
chunker/smart_context.py
chunker/streaming.py
chunker/template_generator.py
chunker/types.py
chunker/vfs.py
chunker/vfs_chunker.py
chunker/_internal/__init__.py
chunker/_internal/cache.py
chunker/_internal/error_handling.py
chunker/_internal/factory.py
chunker/_internal/file_utils.py
chunker/_internal/gc_tuning.py
chunker/_internal/grammar_management.py
chunker/_internal/language_pack.py
chunker/_internal/registry.py
chunker/_internal/user_grammar_tools.py
chunker/_internal/vfs.py
chunker/analysis/__init__.py
chunker/analysis/complexity.py
chunker/analysis/coupling.py
chunker/analysis/semantics.py
chunker/build/__init__.py
chunker/build/builder.py
chunker/build/cross_compile.py
chunker/build/platform.py
chunker/build/system.py
chunker/cicd/__init__.py
chunker/cicd/pipeline.py
chunker/cicd/workflow_validator.py
chunker/cli/grammar_commands.py
chunker/config/__init__.py
chunker/config/profiles.py
chunker/config/strategy_config.py
chunker/context/__init__.py
chunker/context/extractor.py
chunker/context/factory.py
chunker/context/filter.py
chunker/context/scope_analyzer.py
chunker/context/symbol_resolver.py
chunker/context/languages/__init__.py
chunker/context/languages/javascript.py
chunker/context/languages/python.py
chunker/contracts/__init__.py
chunker/contracts/auto_contract.py
chunker/contracts/auto_stub.py
chunker/contracts/build_contract.py
chunker/contracts/build_stub.py
chunker/contracts/cicd_contract.py
chunker/contracts/cicd_stub.py
chunker/contracts/debug_contract.py
chunker/contracts/debug_stub.py
chunker/contracts/devenv_contract.py
chunker/contracts/discovery_contract.py
treesitter_chunker-2.2.2.dist-info/licenses/LICENSE
treesitter_chunker-2.2.2.dist-info/METADATA
treesitter_chunker-2.2.2.dist-info/WHEEL
treesitter_chunker-2.2.2.dist-info/entry_points.txt
treesitter_chunker-2.2.2.dist-info/top_level.txt
treesitter_chunker-2.2.2.dist-info/RECORD
