Metadata-Version: 2.4
Name: treesitter-chunker
Version: 2.2.2
Summary: Semantic code chunker using Tree-sitter for intelligent code analysis
Author-email: Consiliency <dev@consiliency.com>
Maintainer-email: Consiliency <dev@consiliency.com>
License: MIT
Project-URL: Homepage, https://github.com/Consiliency/treesitter-chunker
Project-URL: Documentation, https://treesitter-chunker.readthedocs.io
Project-URL: Repository, https://github.com/Consiliency/treesitter-chunker
Project-URL: Issues, https://github.com/Consiliency/treesitter-chunker/issues
Project-URL: Changelog, https://github.com/Consiliency/treesitter-chunker/blob/main/CHANGELOG.md
Keywords: tree-sitter,code-analysis,chunking,parsing,ast,semantic-analysis,llm,embeddings,rag
Classifier: Development Status :: 5 - Production/Stable
Classifier: Intended Audience :: Developers
Classifier: Intended Audience :: Science/Research
Classifier: Topic :: Software Development :: Libraries :: Python Modules
Classifier: Topic :: Software Development :: Code Generators
Classifier: Topic :: Text Processing :: Linguistic
Classifier: Topic :: Scientific/Engineering :: Artificial Intelligence
Classifier: License :: OSI Approved :: MIT License
Classifier: Programming Language :: Python :: 3
Classifier: Programming Language :: Python :: 3.11
Classifier: Programming Language :: Python :: 3.12
Classifier: Programming Language :: Python :: 3.13
Classifier: Operating System :: OS Independent
Classifier: Operating System :: POSIX :: Linux
Classifier: Operating System :: MacOS :: MacOS X
Classifier: Operating System :: Microsoft :: Windows
Classifier: Typing :: Typed
Requires-Python: >=3.11
License-File: LICENSE
Requires-Dist: tree_sitter<1.0.0,>=0.20.0
Requires-Dist: tree-sitter-language-pack>=0.4.0
Requires-Dist: rich>=13.0.0
Requires-Dist: typer>=0.9.0
Requires-Dist: pyarrow>=15.0.0
Requires-Dist: pyyaml>=6.0
Requires-Dist: pygments>=2.15.0
Requires-Dist: chardet>=5.0.0
Requires-Dist: python-dateutil>=2.9.0
Requires-Dist: gitpython>=3.1.40
Requires-Dist: pathspec>=0.11.0
Requires-Dist: tqdm>=4.66.0
Requires-Dist: tiktoken>=0.7.0
Requires-Dist: tomli-w>=1.0.0
Provides-Extra: dev
Requires-Dist: pytest>=7.4.0; extra == "dev"
Requires-Dist: pytest-cov>=4.1.0; extra == "dev"
Requires-Dist: pytest-xdist>=3.3.1; extra == "dev"
Requires-Dist: pytest-timeout>=2.1.0; extra == "dev"
Requires-Dist: psutil>=5.9.0; extra == "dev"
Requires-Dist: black==25.12.0; extra == "dev"
Requires-Dist: ruff>=0.3.4; extra == "dev"
Requires-Dist: mypy>=1.9.0; extra == "dev"
Requires-Dist: isort>=5.13.0; extra == "dev"
Requires-Dist: pre-commit>=3.5.0; extra == "dev"
Requires-Dist: bandit[toml]>=1.7.8; extra == "dev"
Requires-Dist: types-setuptools; extra == "dev"
Requires-Dist: types-pyyaml; extra == "dev"
Requires-Dist: build; extra == "dev"
Requires-Dist: wheel; extra == "dev"
Requires-Dist: twine; extra == "dev"
Provides-Extra: viz
Requires-Dist: graphviz; extra == "viz"
Provides-Extra: profile
Requires-Dist: memory-profiler>=0.61.0; extra == "profile"
Requires-Dist: line-profiler>=4.1.0; extra == "profile"
Provides-Extra: docs
Requires-Dist: sphinx; extra == "docs"
Requires-Dist: sphinx-rtd-theme; extra == "docs"
Requires-Dist: sphinx-autodoc-typehints; extra == "docs"
Provides-Extra: api
Requires-Dist: fastapi>=0.100.0; extra == "api"
Requires-Dist: uvicorn[standard]>=0.23.0; extra == "api"
Requires-Dist: pydantic>=2.0.0; extra == "api"
Provides-Extra: templates
Requires-Dist: jinja2>=3.0.0; extra == "templates"
Provides-Extra: advanced
Requires-Dist: numpy>=1.20.0; extra == "advanced"
Provides-Extra: full
Requires-Dist: jinja2>=3.0.0; extra == "full"
Requires-Dist: numpy>=1.20.0; extra == "full"
Provides-Extra: all
Requires-Dist: treesitter-chunker[advanced,api,dev,docs,profile,templates,viz]; extra == "all"
Dynamic: license-file
